musictheory/__init__.py
musictheory/chordgenerator.py
musictheory/chords.py
musictheory/musutility.py
musictheory/scales.py
musictheory/temperament.py
musictheory-0.6.0.1.dist-info/LICENSE.txt
musictheory-0.6.0.1.dist-info/METADATA
musictheory-0.6.0.1.dist-info/WHEEL
musictheory-0.6.0.1.dist-info/top_level.txt
musictheory-0.6.0.1.dist-info/RECORD
