Metadata-Version: 2.1
Name: musictheory
Version: 0.6.0.1
Summary: Provides classes for "music set theory"-like analysis.
Home-page: http://pypi.python.org/pypi/musictheory/
Author: Peter Murphy
Author-email: peterkmurphy@gmail.com
License: LICENSE.txt
Keywords: music set theory temperament scale chords
Platform: UNKNOWN
Classifier: Development Status :: 4 - Beta
Classifier: Environment :: Console
Classifier: Environment :: Web Environment
Classifier: Intended Audience :: Developers
Classifier: Intended Audience :: Education
Classifier: Intended Audience :: End Users/Desktop
Classifier: Intended Audience :: Other Audience
Classifier: License :: OSI Approved :: BSD License
Classifier: Operating System :: MacOS
Classifier: Operating System :: Microsoft :: Windows
Classifier: Operating System :: POSIX
Classifier: Programming Language :: Python
Classifier: Topic :: Artistic Software
Classifier: Topic :: Education
Classifier: Topic :: Multimedia :: Sound/Audio
Classifier: Topic :: Other/Nonlisted Topic
Classifier: Topic :: Software Development
Classifier: Topic :: Utilities
